HISTORY.rst
LICENSE
MANIFEST.in
README.rst
setup.cfg
setup.py
docs/Makefile
docs/conf.py
docs/contributing.rst
docs/history.rst
docs/index.rst
docs/installation.rst
docs/make.bat
docs/readme.rst
docs/tutorial.rst
docs/usage.rst
docs/_build/html/_static/ajax-loader.gif
docs/_build/html/_static/comment-bright.png
docs/_build/html/_static/comment-close.png
docs/_build/html/_static/comment.png
docs/_build/html/_static/down-pressed.png
docs/_build/html/_static/down.png
docs/_build/html/_static/file.png
docs/_build/html/_static/minus.png
docs/_build/html/_static/plus.png
docs/_build/html/_static/up-pressed.png
docs/_build/html/_static/up.png
tests/__init__.py
tests/test_datasets.py
tmscc/__init__.py
tmscc/conf.py
tmscc/datasets.py
tmscc/plot.py
tmscc/sampler.py
tmscc/tm.py
tmscc.egg-info/PKG-INFO
tmscc.egg-info/SOURCES.txt
tmscc.egg-info/dependency_links.txt
tmscc.egg-info/not-zip-safe
tmscc.egg-info/requires.txt
tmscc.egg-info/top_level.txt
tmscc/data/klein/labels.txt
tmscc/data/klein/profile.txt