Metadata-Version: 1.1
Name: tmscc
Version: 0.3.0
Summary: A package for reducing dimension of gene expression profilesand doing clustering them.
Home-page: https://github.com/tarohi24/tmscc
Author: Wataru Hirota
Author-email: hirota@whiro.me
License: MIT license
Keywords: tmscc
Platform: UNKNOWN
Classifier: Development Status :: 2 - Pre-Alpha
Classifier: Intended Audience :: Developers
Classifier: License :: OSI Approved :: MIT License
Classifier: Natural Language :: English
Classifier: Programming Language :: Python :: 3
Classifier: Programming Language :: Python :: 3.4
Classifier: Programming Language :: Python :: 3.5
Classifier: Programming Language :: Python :: 3.6
